memorix/__init__.py
memorix/config.py
memorix/embedder.py
memorix/memory_api.py
memorix/metadata_store.py
memorix/vector_store.py
memorix_ai-0.1.0.dist-info/licenses/LICENSE
memorix_ai-0.1.0.dist-info/METADATA
memorix_ai-0.1.0.dist-info/WHEEL
memorix_ai-0.1.0.dist-info/top_level.txt
memorix_ai-0.1.0.dist-info/RECORD
