Metadata-Version: 2.4
Name: memorix-ai
Version: 0.1.0
Summary: The memory layer for AI agents
Author-email: Memorix AI <founder@memorix.ai>
License-Expression: Apache-2.0
Project-URL: Homepage, https://github.com/memorix-ai/memorix-ai
Project-URL: Documentation, https://docs.memorix.ai
Project-URL: Repository, https://github.com/memorix-ai/memorix-ai.git
Project-URL: Bug Tracker, https://github.com/memorix-ai/memorix-ai/issues
Project-URL: Discussions, https://github.com/memorix-ai/memorix-ai/discussions
Requires-Python: >=3.8
License-File: LICENSE
Requires-Dist: faiss-cpu
Requires-Dist: pydantic>=2.0
Requires-Dist: openai
Requires-Dist: numpy>=1.21.0
Requires-Dist: pyyaml>=6.0
Provides-Extra: dev
Requires-Dist: pytest>=7.0.0; extra == "dev"
Requires-Dist: pytest-cov>=4.0.0; extra == "dev"
Requires-Dist: black>=22.0.0; extra == "dev"
Requires-Dist: isort>=5.0.0; extra == "dev"
Requires-Dist: flake8>=5.0.0; extra == "dev"
Requires-Dist: mypy>=1.0.0; extra == "dev"
Provides-Extra: openai
Requires-Dist: openai>=1.0.0; extra == "openai"
Provides-Extra: gemini
Requires-Dist: google-generativeai>=0.3.0; extra == "gemini"
Provides-Extra: sentence-transformers
Requires-Dist: sentence-transformers>=2.0.0; extra == "sentence-transformers"
Requires-Dist: torch>=1.9.0; extra == "sentence-transformers"
Provides-Extra: qdrant
Requires-Dist: qdrant-client>=1.0.0; extra == "qdrant"
Provides-Extra: all
Requires-Dist: memorix-ai[gemini,openai,qdrant,sentence-transformers]; extra == "all"
Dynamic: license-file
